odoo/addons/stock_inventory_verification_request/README.rst
odoo/addons/stock_inventory_verification_request/__init__.py
odoo/addons/stock_inventory_verification_request/__manifest__.py
odoo/addons/stock_inventory_verification_request/data/slot_verification_request_sequence.xml
odoo/addons/stock_inventory_verification_request/i18n/am.po
odoo/addons/stock_inventory_verification_request/i18n/ar.po
odoo/addons/stock_inventory_verification_request/i18n/bg.po
odoo/addons/stock_inventory_verification_request/i18n/bs.po
odoo/addons/stock_inventory_verification_request/i18n/ca.po
odoo/addons/stock_inventory_verification_request/i18n/ca_ES.po
odoo/addons/stock_inventory_verification_request/i18n/cs.po
odoo/addons/stock_inventory_verification_request/i18n/cs_CZ.po
odoo/addons/stock_inventory_verification_request/i18n/da.po
odoo/addons/stock_inventory_verification_request/i18n/de.po
odoo/addons/stock_inventory_verification_request/i18n/el_GR.po
odoo/addons/stock_inventory_verification_request/i18n/en_GB.po
odoo/addons/stock_inventory_verification_request/i18n/es.po
odoo/addons/stock_inventory_verification_request/i18n/es_AR.po
odoo/addons/stock_inventory_verification_request/i18n/es_CL.po
odoo/addons/stock_inventory_verification_request/i18n/es_CO.po
odoo/addons/stock_inventory_verification_request/i18n/es_CR.po
odoo/addons/stock_inventory_verification_request/i18n/es_DO.po
odoo/addons/stock_inventory_verification_request/i18n/es_EC.po
odoo/addons/stock_inventory_verification_request/i18n/es_ES.po
odoo/addons/stock_inventory_verification_request/i18n/es_MX.po
odoo/addons/stock_inventory_verification_request/i18n/es_PE.po
odoo/addons/stock_inventory_verification_request/i18n/es_PY.po
odoo/addons/stock_inventory_verification_request/i18n/es_VE.po
odoo/addons/stock_inventory_verification_request/i18n/et.po
odoo/addons/stock_inventory_verification_request/i18n/eu.po
odoo/addons/stock_inventory_verification_request/i18n/fa.po
odoo12_addon_stock_inventory_verification_request-12.0.3.0.1.dist-info/METADATA
odoo12_addon_stock_inventory_verification_request-12.0.3.0.1.dist-info/WHEEL
odoo12_addon_stock_inventory_verification_request-12.0.3.0.1.dist-info/top_level.txt
odoo12_addon_stock_inventory_verification_request-12.0.3.0.1.dist-info/RECORD
