Metadata-Version: 2.1
Name: odoo12-addon-stock-inventory-verification-request
Version: 12.0.3.0.1
Summary: Adds the capability to request a Slot Verification when a inventory is Pending to Approve
Home-page: https://github.com/OCA/stock-logistics-warehouse
Author: ForgeFlow, Odoo Community Association (OCA)
Author-email: support@odoo-community.org
License: AGPL-3
Platform: UNKNOWN
Classifier: Programming Language :: Python
Classifier: Framework :: Odoo
Classifier: Framework :: Odoo :: 12.0
Classifier: License :: OSI Approved :: GNU Affero General Public License v3
Requires-Python: >=3.5
Requires-Dist: odoo12-addon-stock-inventory-discrepancy
Requires-Dist: odoo (<12.1dev,>=12.0a)
